[
    {
        "id": 1,
        "name": "Cadz",
        "vocation": "Arqueiro",
        "level": 14,
        "experience": 61758,
        "server": "Onix"
    },
    {
        "id": 2,
        "name": "Dark Haunter",
        "vocation": "Arqueiro",
        "level": 9,
        "experience": 13905,
        "server": "Onix"
    },
    {
        "id": 3,
        "name": "Miihzinha",
        "vocation": "Arqueiro",
        "level": 9,
        "experience": 13413,
        "server": "Onix"
    },
    {
        "id": 4,
        "name": "Polly Gray",
        "vocation": "Arqueiro",
        "level": 9,
        "experience": 12573,
        "server": "Onix"
    },
    {
        "id": 5,
        "name": "Nostradamus",
        "vocation": "Arqueiro",
        "level": 7,
        "experience": 5562,
        "server": "Onix"
    },
    {
        "id": 6,
        "name": "Brunoaf",
        "vocation": "Arqueiro",
        "level": 6,
        "experience": 4950,
        "server": "Onix"
    },
    {
        "id": 7,
        "name": "Drunken Lightning",
        "vocation": "Arqueiro",
        "level": 6,
        "experience": 3492,
        "server": "Onix"
    },
    {
        "id": 8,
        "name": "Moonk",
        "vocation": "Arqueiro",
        "level": 6,
        "experience": 3321,
        "server": "Onix"
    },
    {
        "id": 9,
        "name": "Child",
        "vocation": "Arqueiro",
        "level": 5,
        "experience": 2862,
        "server": "Onix"
    },
    {
        "id": 10,
        "name": "Iocasan",
        "vocation": "Arqueiro",
        "level": 5,
        "experience": 2709,
        "server": "Onix"
    },
    {
        "id": 11,
        "name": "Ferreira Ferrada",
        "vocation": "Arqueiro",
        "level": 5,
        "experience": 1827,
        "server": "Onix"
    },
    {
        "id": 12,
        "name": "Buffa Barbaro",
        "vocation": "Arqueiro",
        "level": 5,
        "experience": 1737,
        "server": "Onix"
    },
    {
        "id": 13,
        "name": "Ivan Luiz",
        "vocation": "Arqueiro",
        "level": 5,
        "experience": 1719,
        "server": "Onix"
    },
    {
        "id": 14,
        "name": "Shane Walsh",
        "vocation": "Arqueiro",
        "level": 4,
        "experience": 1440,
        "server": "Onix"
    },
    {
        "id": 15,
        "name": "Jefao Rpzin",
        "vocation": "Arqueiro",
        "level": 4,
        "experience": 1035,
        "server": "Onix"
    },
    {
        "id": 16,
        "name": "Cabulosao",
        "vocation": "Arqueiro",
        "level": 4,
        "experience": 981,
        "server": "Onix"
    },
    {
        "id": 17,
        "name": "Bruno Meira",
        "vocation": "Arqueiro",
        "level": 4,
        "experience": 837,
        "server": "Onix"
    },
    {
        "id": 18,
        "name": "Billyofhell",
        "vocation": "Arqueiro",
        "level": 4,
        "experience": 828,
        "server": "Onix"
    },
    {
        "id": 19,
        "name": "Laneto Demonic",
        "vocation": "Arqueiro",
        "level": 3,
        "experience": 639,
        "server": "Onix"
    },
    {
        "id": 20,
        "name": "Qyop",
        "vocation": "Arqueiro",
        "level": 3,
        "experience": 621,
        "server": "Onix"
    },
    {
        "id": 21,
        "name": "Rayuka",
        "vocation": "Arqueiro",
        "level": 3,
        "experience": 594,
        "server": "Onix"
    },
    {
        "id": 22,
        "name": "Biguazinho",
        "vocation": "Arqueiro",
        "level": 3,
        "experience": 486,
        "server": "Onix"
    },
    {
        "id": 23,
        "name": "Bixobruto",
        "vocation": "Arqueiro",
        "level": 3,
        "experience": 360,
        "server": "Onix"
    },
    {
        "id": 24,
        "name": "Edyzzerah",
        "vocation": "Arqueiro",
        "level": 3,
        "experience": 306,
        "server": "Onix"
    },
    {
        "id": 25,
        "name": "Bone War",
        "vocation": "Arqueiro",
        "level": 3,
        "experience": 297,
        "server": "Onix"
    },
    {
        "id": 26,
        "name": "Armor",
        "vocation": "Arqueiro",
        "level": 3,
        "experience": 297,
        "server": "Onix"
    },
    {
        "id": 27,
        "name": "Drykan",
        "vocation": "Arqueiro",
        "level": 3,
        "experience": 234,
        "server": "Onix"
    },
    {
        "id": 28,
        "name": "Muzzuco",
        "vocation": "Arqueiro",
        "level": 3,
        "experience": 234,
        "server": "Onix"
    },
    {
        "id": 29,
        "name": "Biaa",
        "vocation": "Arqueiro",
        "level": 2,
        "experience": 162,
        "server": "Onix"
    },
    {
        "id": 30,
        "name": "Lucas Sandi",
        "vocation": "Arqueiro",
        "level": 2,
        "experience": 126,
        "server": "Onix"
    },
    {
        "id": 31,
        "name": "Sakuyamon",
        "vocation": "Arqueiro",
        "level": 2,
        "experience": 99,
        "server": "Onix"
    },
    {
        "id": 32,
        "name": "Gorobin",
        "vocation": "Arqueiro",
        "level": 2,
        "experience": 72,
        "server": "Onix"
    },
    {
        "id": 33,
        "name": "Ephiny",
        "vocation": "Arqueiro",
        "level": 2,
        "experience": 54,
        "server": "Onix"
    },
    {
        "id": 34,
        "name": "Oriax",
        "vocation": "Arqueiro",
        "level": 2,
        "experience": 36,
        "server": "Onix"
    },
    {
        "id": 35,
        "name": "Linkle",
        "vocation": "Arqueiro",
        "level": 2,
        "experience": 27,
        "server": "Onix"
    },
    {
        "id": 36,
        "name": "Abrakadraba",
        "vocation": "Arqueiro",
        "level": 2,
        "experience": 18,
        "server": "Onix"
    },
    {
        "id": 37,
        "name": "Chaells",
        "vocation": "Arqueiro",
        "level": 2,
        "experience": 9,
        "server": "Onix"
    },
    {
        "id": 38,
        "name": "Massarico",
        "vocation": "Arqueiro",
        "level": 30,
        "experience": 634095,
        "server": "Ruby"
    },
    {
        "id": 39,
        "name": "Zerphiros",
        "vocation": "Arqueiro",
        "level": 10,
        "experience": 18135,
        "server": "Ruby"
    },
    {
        "id": 40,
        "name": "Bubba Shibaba",
        "vocation": "Arqueiro",
        "level": 5,
        "experience": 2889,
        "server": "Ruby"
    },
    {
        "id": 41,
        "name": "Fenhir The Wolf",
        "vocation": "Arqueiro",
        "level": 3,
        "experience": 387,
        "server": "Ruby"
    },
    {
        "id": 42,
        "name": "Tyaze",
        "vocation": "Arqueiro",
        "level": 2,
        "experience": 180,
        "server": "Ruby"
    },
    {
        "id": 43,
        "name": "Tratorista",
        "vocation": "Arqueiro",
        "level": 2,
        "experience": 126,
        "server": "Ruby"
    },
    {
        "id": 44,
        "name": "Laura",
        "vocation": "Arqueiro",
        "level": 2,
        "experience": 54,
        "server": "Ruby"
    },
    {
        "id": 45,
        "name": "Raytay",
        "vocation": "Arqueiro",
        "level": 11,
        "experience": 26940,
        "server": "Jasper"
    },
    {
        "id": 46,
        "name": "Jdsofc",
        "vocation": "Arqueiro",
        "level": 5,
        "experience": 2367,
        "server": "Jasper"
    },
    {
        "id": 47,
        "name": "Don Konduktor",
        "vocation": "Arqueiro",
        "level": 3,
        "experience": 450,
        "server": "Jasper"
    },
    {
        "id": 48,
        "name": "Hania Zuza",
        "vocation": "Arqueiro",
        "level": 3,
        "experience": 441,
        "server": "Jasper"
    },
    {
        "id": 49,
        "name": "Mighz",
        "vocation": "Arqueiro",
        "level": 3,
        "experience": 234,
        "server": "Jasper"
    }
]